Workbook

Sheet Dashboard
A1: HUL Financial Dashboard

Sheet Income Statement
B1: Standalone Statement of Profit and Loss
B4: Particulars | C4: As at 31st March 2021 | D4: As at 31st March 2022 | E4: As at 31st March 2023 | F4: As at 31st March 2024 | G4: As at 31st March 2025 | H4: As at 31st March 2026
B5: INCOME
B6: Revenue from operations | C6: 45996 | D6: 51193 | E6: 59144 | F6: 60469 | G6: 59676 | H6: 61975
B7: Other income | C7: 513 | D7: 393 | E7: 640 | F7: 973 | G7: 1177 | H7: 959
B8: TOTAL INCOME | C8: =SUM(C6:C7) -> 46509 | D8: =SUM(D6:D7) -> 51586 | E8: =SUM(E6:E7) -> 59784 | F8: =SUM(F6:F7) -> 61442 | G8: =G6+G7 -> 60853 | H8: =H6+H7 -> 62934
B9: EXPENSES
B10: Cost of materials consumed | C10: 14951 | D10: 15869 | E10: 19229 | F10: 17791 | G10: 17274 | H10: 18726
B11: Purchases of stock-in-trade | C11: 7117 | D11: 9274 | E11: 11968 | F11: 11544 | G11: 12172 | H11: 12753
B12: Changes in inventories of finished goods work-in-progress and stock-in-trade | C12: -391 | D12: -19 | E12: -53 | F12: -8 | G12: -78 | H12: -395
B13: Employee benefits expense | C13: 2229 | D13: 2399 | E13: 2665 | F13: 2782 | G13: 2715 | H13: 2843
B14: Finance costs | C14: 108 | D14: 98 | E14: 101 | F14: 302 | G14: 350 | H14: 363
B15: Depreciation and amortisation expense | C15: 1012 | D15: 1025 | E15: 1030 | F15: 1097 | G15: 1122 | H15: 1186
B16: Other expenses | C16: 10766 | D16: 11167 | E16: 11703 | F16: 14170 | G16: 13449 | H16: 13584
B17: TOTAL EXPENSES | C17: =SUM(C10:C16) -> 35792 | D17: =SUM(D10:D16) -> 39813 | E17: =SUM(E10:E16) -> 46643 | F17: =SUM(F10:F16) -> 47678 | G17: =SUM(G10:G16) -> 47004 | H17: =SUM(H10:H16) -> 49060
B18: Profit before exceptional items and tax | C18: =C8-C17 -> 10717 | D18: =D8-D17 -> 11773 | E18: =E8-E17 -> 13141 | F18: =F8-F17 -> 13764 | G18: =G8-G17 -> 13849 | H18: =H8-H17 -> 13874
B19: Exceptional items | C19: -227 | D19: -34 | E19: -62 | F19: -89 | G19: 464 | H19: 206
B20: Profit before tax | C20: =SUM(C18:C19) -> 10490 | D20: =SUM(D18:D19) -> 11739 | E20: =SUM(E18:E19) -> 13079 | F20: =SUM(F18:F19) -> 13675 | G20: =G18+G19 -> 14313 | H20: =H18+H19 -> 14080
B21: Tax expense
B22: Current tax | C22: -2458 | D22: -2778 | E22: -2922 | F22: -3446 | G22: -3523 | H22: -3070
B23: Deferred tax | C23: -78 | D23: -143 | E23: -195 | F23: -115 | G23: -137 | H23: 10
B24: PROFIT FOR THE YEAR | C24: =C20+C22+C23 -> 7954 | D24: =D20+D22+D23 -> 8818 | E24: =E20+E22+E23 -> 9962 | F24: =F20+F22+F23 -> 10114 | G24: =G20+G22+G23 -> 10653 | H24: =H20+H22+H23 -> 11020

Sheet Balance Sheet
A2: Standalone Balance Sheet
A3: ₹ crore
A5: Particulars | B5: As at 31st March 2021 | C5: As at 31st March 2022 | D5: As at 31st March 2023 | E5: As at 31st March 2024 | F5: As at 31st March 2025 | G5: As at 31st March 2026 | H5: As at 31 March 2027 E | I5: As at 31 March 2028 E | J5: As at 31 March 2029 E | K5: As at 31 March 2030 E
A6: ASSETS
A7: Non Current assets
A8: Property, Plant & Equipment | B8: 5786 | C8: 5813 | D8: 6189 | E8: 7178 | F8: 7710 | G8: 7191 | H8: =G8+(Assumption!G19*'FY 26-27E Projected'!I6)-'FY 26-27E Projected'!I16 -> 7131.4895 | I8: =H8+(Assumption!H19*'FY 26-27E Projected'!J6)-'FY 26-27E Projected'!J16 -> 7027.4078 | J8: =I8+(Assumption!I19*'FY 26-27E Projected'!K6)-'FY 26-27E Projected'!K16 -> 6873.3571 | K8: =J8+(Assumption!J19*'FY 26-27E Projected'!L6)-'FY 26-27E Projected'!L16 -> 6663.4349
A9: Capital Work in Progress | B9: 623 | C9: 901 | D9: 1020 | E9: 915 | F9: 956 | G9: 833 | H9: =Table3[[#This Row],[As at 31st March 2026]] -> 833 | I9: =H9 -> 833 | J9: =I9 -> 833 | K9: =J9 -> 833
A10: Goodwill | B10: 17316 | C10: 17316 | D10: 17316 | E10: 17316 | F10: 17316 | G10: 17281 | H10: =Table3[[#This Row],[As at 31st March 2026]] -> 17281 | I10: =H10 -> 17281 | J10: =I10 -> 17281 | K10: =J10 -> 17281
A11: Other tengible assets | B11: 27925 | C11: 27905 | D11: 27900 | E11: 27885 | F11: 27881 | G11: 27947 | H11: =Table3[[#This Row],[As at 31st March 2026]] -> 27947 | I11: =H11 -> 27947 | J11: =I11 -> 27947 | K11: =J11 -> 27947
A12: Financial Assets
A13: Investment in Subsidiaries and Joint Venture | B13: 310 | C13: 610 | D13: 981 | E13: 981 | F13: 986 | G13: 4632 | H13: =Table3[[#This Row],[As at 31st March 2026]] -> 4632 | I13: =H13 -> 4632 | J13: =I13 -> 4632 | K13: =J13 -> 4632
A14: Investments | B14: 2 | C14: 2 | D14: 2 | E14: 2 | F14: 2 | G14: 111 | H14: =Table3[[#This Row],[As at 31st March 2026]] -> 111 | I14: =H14 -> 111 | J14: =I14 -> 111 | K14: =J14 -> 111
A15: Loans | B15: 385 | C15: 541 | D15: 339 | E15: 392 | F15: 332 | G15: 343 | H15: =Table3[[#This Row],[As at 31st March 2026]] -> 343 | I15: =H15 -> 343 | J15: =I15 -> 343 | K15: =J15 -> 343
A16: Other Financial assets | B16: 748 | C16: 720 | D16: 715 | E16: 714 | F16: 744 | G16: 691 | H16: =Table3[[#This Row],[As at 31st March 2026]] -> 691 | I16: =H16 -> 691 | J16: =I16 -> 691 | K16: =J16 -> 691
A17: Non- current Tax asset (net) | B17: 1200 | C17: 1107 | D17: 1115 | E17: 1118 | F17: 1144 | G17: 1078 | H17: =Table3[[#This Row],[As at 31st March 2026]] -> 1078 | I17: =H17 -> 1078 | J17: =I17 -> 1078 | K17: =J17 -> 1078
A18: Other Non current assets | B18: 181 | C18: 175 | D18: 199 | E18: 279 | F18: 343 | G18: 340 | H18: =Table3[[#This Row],[As at 31st March 2026]] -> 340 | I18: =H18 -> 340 | J18: =I18 -> 340 | K18: =J18 -> 340
A19: Total Non current Assets | B19: =SUM(B8:B18) -> 54476 | C19: =SUM(C8:C18) -> 55090 | D19: =SUM(D8:D18) -> 55776 | E19: =SUM(E8:E18) -> 56780 | F19: =SUM(F8:F18) -> 57414 | G19: =SUM(G8:G18) -> 60447 | H19: =SUM(H8:H18) -> 60387.489 | I19: =SUM(I8:I18) -> 60283.408 | ... K19: =SUM(K8:K18) -> 59919.435
A20: Current Assets
A21: Inventories | B21: 3383 | C21: 3890 | D21: 4031 | E21: 3812 | F21: 4161 | G21: 4383 | H21: =(Assumption!G15/365)*'FY 26-27E Projected'!I11 -> 4649.4303 | I21: =(Assumption!H15/365)*'FY 26-27E Projected'!J11 -> 4943.382 | J21: =(Assumption!I15/365)*'FY 26-27E Projected'!K11 -> 5255.9182 | K21: =(Assumption!J15/365)*'FY 26-27E Projected'!L11 -> 5588.2139
A22: Financial Assets
A23: Investment | B23: 2683 | C23: 3510 | D23: 2811 | E23: 4510 | F23: 3614 | G23: 4136 | H23: =Table3[[#This Row],[As at 31st March 2026]] -> 4136 | I23: =H23 -> 4136 | J23: =I23 -> 4136 | K23: =J23 -> 4136
A24: Trade Receivables | B24: 1648 | C24: 1932 | D24: 2735 | E24: 2690 | F24: 3450 | G24: 3037 | H24: =(Assumption!G14/365)*'FY 26-27E Projected'!I6 -> 3100.726 | I24: =(Assumption!H14/365)*'FY 26-27E Projected'!J6 -> 3296.7637 | J24: =(Assumption!I14/365)*'FY 26-27E Projected'!K6 -> 3505.1955 | K24: =(Assumption!J14/365)*'FY 26-27E Projected'!L6 -> 3726.805
A25: Cash and cash equivalents | B25: 1740 | C25: 988 | D25: 586 | E25: 609 | F25: 5947 | G25: 2286 | H25: ='Cash Flow Statement'!H75 -> 4103.9135 | I25: ='Cash Flow Statement'!I75 -> 6620.6288 | J25: ='Cash Flow Statement'!J75 -> 9376.6607 | K25: ='Cash Flow Statement'!K75 -> 12392.424
A26: Bank balance other than cash and cash equivalents mention above | B26: 2581 | C26: 2630 | D26: 3836 | E26: 6607 | F26: 1346 | G26: 544 | H26: =Table3[[#This Row],[As at 31st March 2026]] -> 544 | I26: =H26 -> 544 | J26: =I26 -> 544 | K26: =J26 -> 544
A27: Loans | B27: 34 | C27: 34 | D27: 35 | E27: 37 | F27: 45 | G27: 49 | H27: =Table3[[#This Row],[As at 31st March 2026]] -> 49 | I27: =H27 -> 49 | J27: =I27 -> 49 | K27: =J27 -> 49
A28: Other Financial assets | B28: 1116 | C28: 1070 | D28: 1391 | E28: 1416 | F28: 1469 | G28: 1947 | H28: =Table3[[#This Row],[As at 31st March 2026]] -> 1947 | I28: =H28 -> 1947 | J28: =I28 -> 1947 | K28: =J28 -> 1947
A29: Current tax Assets (net) | F29: - | G29: 154 | H29: =Table3[[#This Row],[As at 31st March 2026]] -> 154 | I29: =H29 -> 154 | J29: =I29 -> 154 | K29: =J29 -> 154
A30: Other current Assets | B30: 438 | C30: 580 | D30: 612 | E30: 603 | F30: 844 | G30: 985 | H30: =Table3[[#This Row],[As at 31st March 2026]] -> 985 | I30: =H30 -> 985 | J30: =I30 -> 985 | K30: =J30 -> 985
A31: Asset hold for sale | B31: 17 | C31: 13 | D31: 12 | E31: 12 | F31: 23 | G31: 14 | H31: =Table3[[#This Row],[As at 31st March 2026]] -> 14 | I31: =H31 -> 14 | J31: =I31 -> 14 | K31: =J31 -> 14
A32: Total current assets | B32: =SUM(B21:B31) -> 13640 | C32: =SUM(C21:C31) -> 14647 | D32: =SUM(D21:D31) -> 16049 | E32: =SUM(E21:E31) -> 20296 | F32: =SUM(F21:F31) -> 20899 | G32: =SUM(G21:G31) -> 17535 | H32: =SUM(H21:H31) -> 19683.07 | I32: =SUM(I21:I31) -> 22689.774 | ... K32: =SUM(K21:K31) -> 29536.443
A33: Total Assets | B33: =B32+B19 -> 68116 | C33: =C32+C19 -> 69737 | D33: =D32+D19 -> 71825 | E33: =E32+E19 -> 77076 | F33: =F32+F19 -> 78313 | G33: =G32+G19 -> 77982 | H33: =H32+H19 -> 80070.559 | I33: =I32+I19 -> 82973.182 | ... K33: =K32+K19 -> 89455.878
A34: EQUITY AND LIABILITES
A35: Equity
A36: Equity share capital | B36: 235 | C36: 235 | D36: 235 | E36: 235 | F36: 235 | G36: 235 | H36: =G36 -> 235 | I36: =H36 -> 235 | J36: =I36 -> 235 | K36: =J36 -> 235
A37: Other equtiy | B37: 47199 | C37: 48525 | D37: 49986 | E37: 50738 | F37: 48918 | G37: 48988 | H37: =G37+'FY 26-27E Projected'!I24-(Assumption!G20*'FY 26-27E Projected'!I24) -> 50255.858 | I37: =H37+'FY 26-27E Projected'!J24-(Assumption!H20*'FY 26-27E Projected'!J24) -> 51597.081 | J37: =I37+'FY 26-27E Projected'!K24-(Assumption!I20*'FY 26-27E Projected'!K24) -> 53016.093 | K37: =J37+'FY 26-27E Projected'!L24-(Assumption!J20*'FY 26-27E Projected'!L24) -> 54517.583
A38: Total equtiy | B38: =SUM(B36:B37) -> 47434 | C38: =SUM(C36:C37) -> 48760 | D38: =SUM(D36:D37) -> 50221 | E38: =SUM(E36:E37) -> 50973 | F38: =SUM(F36:F37) -> 49153 | G38: =SUM(G36:G37) -> 49223 | H38: =SUM(H36:H37) -> 50490.858 | I38: =SUM(I36:I37) -> 51832.081 | ... K38: =SUM(K36:K37) -> 54752.583
A39: Liabilities
A40: Non current liabilities
A41: Financial liabilities
A42: lease liabilities | B42: 679 | C42: 686 | D42: 746 | E42: 1034 | F42: 1157 | G42: 994 | H42: =G42 -> 994 | I42: =H42 -> 994 | J42: =I42 -> 994 | K42: =J42 -> 994
A43: Other financial liabilities | B43: 266 | C43: 329 | D43: 495 | E43: 430 | F43: 647 | G43: 819 | H43: =G43 -> 819 | I43: =H43 -> 819 | J43: =I43 -> 819 | K43: =J43 -> 819
A44: Provisions | B44: 1551 | C44: 1553 | D44: 1335 | E44: 1551 | F44: 1509 | G44: 1663 | H44: =G44 -> 1663 | I44: =H44 -> 1663 | J44: =I44 -> 1663 | K44: =J44 -> 1663
A45: Deffered tax liablities (net) | B45: 5986 | C45: 6141 | D45: 6325 | E45: 6454 | F45: 6583 | G45: 6649 | H45: =G45 -> 6649 | I45: =H45 -> 6649 | J45: =I45 -> 6649 | K45: =J45 -> 6649
A46: Non-current tax liabilities (net) | B46: 1359 | C46: 1324 | D46: 1076 | E46: 4231 | F46: 3592 | G46: 3685 | H46: =G46 -> 3685 | I46: =H46 -> 3685 | J46: =I46 -> 3685 | K46: =J46 -> 3685
A47: Total - Non-current liabilities | B47: =SUM(B42:B46) -> 9841 | C47: =SUM(C42:C46) -> 10033 | D47: =SUM(D42:D46) -> 9977 | E47: =SUM(E42:E46) -> 13700 | F47: =SUM(F42:F46) -> 13488 | G47: =SUM(G42:G46) -> 13810 | H47: =SUM(H42:H46) -> 13810 | I47: =SUM(I42:I46) -> 13810 | ... K47: =SUM(K42:K46) -> 13810
A48: Current liabilities
A49: Financial liabilities
A50: lease liabilities | B50: 264 | C50: 285 | D50: 293 | E50: 340 | F50: 380 | G50: 331 | H50: =G50 -> 331 | I50: =H50 -> 331 | J50: =I50 -> 331 | K50: =J50 -> 331
A51: Trade payble
A52: Total outstanding dues of micro enterprises and small enterprises | B52: 64 | C52: 56 | D52: 89 | E52: 222 | F52: 231 | G52: 396 | H52: 0 | I52: 0 | J52: 0 | K52: 0
A53: Total outstanding dues of creditors other than micro enterprises and small enterprises | B53: 8563 | C53: 8808 | D53: 9302 | E53: 9926 | F53: 10767 | G53: 12517 | H53: =(Assumption!G16/365)*'FY 26-27E Projected'!I11 -> 13733.702 | I53: =(Assumption!H16/365)*'FY 26-27E Projected'!J11 -> 15295.101 | J53: =(Assumption!I16/365)*'FY 26-27E Projected'!K11 -> 16999.038 | K53: =(Assumption!J16/365)*'FY 26-27E Projected'!L11 -> 18857.295
A54: Other financial liabilities | B54: 892 | C54: 823 | D54: 829 | E54: 797 | F54: 825 | G54: 760 | H54: =G54 -> 760 | I54: =H54 -> 760 | J54: =I54 -> 760 | K54: =J54 -> 760
A55: other current liabilities | B55: 567 | C55: 638 | D55: 735 | E55: 789 | F55: 921 | G55: 688 | H55: =G55 -> 688 | I55: =H55 -> 688 | J55: =I55 -> 688 | K55: =J55 -> 688
A56: Provisions | B56: 491 | C56: 334 | D56: 379 | E56: 329 | F56: 661 | G56: 257 | H56: =G56 -> 257 | I56: =H56 -> 257 | J56: =I56 -> 257 | K56: =J56 -> 257
A57: current tax liabilities | D57: - | E57: - | F57: 1887 | G57: 0 | H57: =G57 -> 0 | I57: =H57 -> 0 | J57: =I57 -> 0 | K57: =J57 -> 0
A58: Total - Current liabilities | B58: =SUM(B50:B57) -> 10841 | C58: =SUM(C50:C57) -> 10944 | D58: =SUM(D50:D57) -> 11627 | E58: =SUM(E50:E57) -> 12403 | F58: =SUM(F50:F57) -> 15672 | G58: =SUM(G50:G57) -> 14949 | H58: =SUM(H50:H57) -> 15769.702 | I58: =SUM(I50:I57) -> 17331.101 | ... K58: =SUM(K50:K57) -> 20893.295
A59: TOTAL EQUITY AND LIABILITIES | B59: =SUM(B38+B47+B58) -> 68116 | C59: =SUM(C38+C47+C58) -> 69737 | D59: =SUM(D38+D47+D58) -> 71825 | E59: =SUM(E38+E47+E58) -> 77076 | F59: =F58+F47+F38 -> 78313 | G59: =G58+G47+G38 -> 77982 | H59: =H58+H47+H38 -> 80070.559 | I59: =I58+I47+I38 -> 82973.182 | J59: =J58+J47+J38 -> 86096.131 | K59: =K58+K47+K38 -> 89455.878
A61: check | B61: =ROUND(B33 - B59, 0) -> 0 | C61: =ROUND(C33 - C59, 0) -> 0 | D61: =ROUND(D33 - D59, 0) -> 0 | E61: =ROUND(E33 - E59, 0) -> 0 | F61: =ROUND(F33 - F59, 0) -> 0 | G61: =ROUND(G33 - G59, 0) -> 0 | H61: =ROUND(H33 - H59, 0) -> 0 | I61: =ROUND(I33 - I59, 0) -> 0 | ... K61: =ROUND(K33 - K59, 0) -> 0

Sheet Cash Flow Statement
A1: Standalone Statement of Cash Flows
A2: ₹ crore
A3: Particulars | B3: As at 31st March 2021 | C3: As at 31st March 2022 | D3: As at 31st March 2023 | E3: As at 31st March 2024 | F3: As at 31st March 2025 | G3: As at 31st March 2026 | H3: As at 31 March 2027 E | I3: As at 31 March 2028 E | J3: As at 31 March 2029 E | K3: As at 31 March 2030 E
A4: A CASH FLOWS FROM OPERATING ACTIVITIES:
A5: Profit before tax from countinuing operations | B5: 10490 | C5: 11739 | D5: 13079 | E5: 13675 | F5: 14313 | G5: 14080 | H5: ='FY 26-27E Projected'!I22 -> 14837.305 | I5: ='FY 26-27E Projected'!J22 -> 15695.876 | J5: ='FY 26-27E Projected'!K22 -> 16606.213 | K5: ='FY 26-27E Projected'!L22 -> 17571.423
A6: Profit / loss before tax from discounted operations | B6: - | C6: - | D6: - | E6: - | F6: -13 | G6: 4336 | H6: 0 | I6: 0 | J6: 0 | K6: 0
A7: Adjustement for:
A8: Depricitain and amortisation expense | B8: 1069 | C8: 1040 | D8: 1045 | E8: 1097 | F8: 1232 | G8: 1289 | H8: ='FY 26-27E Projected'!I16 -> 1306.6601 | I8: ='FY 26-27E Projected'!J16 -> 1430.0799 | J8: ='FY 26-27E Projected'!K16 -> 1563.8828 | K8: ='FY 26-27E Projected'!L16 -> 1708.8883
A9: Government grant accrued (net) | B9: 13 | C9: - | D9: - | E9: - | F9: - | G9: - | H9: 0 | I9: 0 | J9: 0 | K9: 0
A10: Contingent consideration true up for business combination | B10: -22 | C10: -9 | D10: -2 | E10: - | F10: - | G10: - | H10: 0 | I10: 0 | J10: 0 | K10: 0
A11: loss on sale of Property, Plant and equipment | B11: -57 | C11: -99 | D11: -102 | E11: 17 | F11: 15 | G11: 39 | H11: 0 | I11: 0 | J11: 0 | K11: 0
A12: Fair value loss/gain on financial liability on acqusition | B12: - | C12: - | D12: - | E12: -37 | F12: 5 | G12: 34 | H12: 0 | I12: 0 | J12: 0 | K12: 0
A13: Interest Income | B13: -350 | C13: -207 | D13: -425 | E13: -551 | F13: -763 | G13: -546 | H13: 0 | I13: 0 | J13: 0 | K13: 0
A14: Dividend Income | B14: -102 | C14: -131 | D14: -118 | E14: -176 | F14: -169 | G14: -230 | H14: 0 | I14: 0 | J14: 0 | K14: 0
A15: Other non operating income - Fair value gain on investment | B15: -61 | C15: -55 | D15: -97 | E15: -246 | F15: -245 | G15: -183 | H15: 0 | I15: 0 | J15: 0 | K15: 0
A16: Profit on sale of stake in joint venture | B16: - | C16: - | D16: - | E16: - | F16: - | G16: -228 | H16: 0 | I16: 0 | J16: 0 | K16: 0
A17: Interest expense | B17: 108 | C17: 98 | D17: 101 | E17: 285 | F17: 341 | G17: 376 | H17: 0 | I17: 0 | J17: 0 | K17: 0
A18: Profit on sale of water purification business | B18: - | C18: - | D18: - | E18: - | F18: -595 | G18: - | H18: 0 | I18: 0 | J18: 0 | K18: 0
A19: Movement of provision towards litigation | B19: - | C19: - | D19: - | E19: -159 | F19: - | G19: - | H19: 0 | I19: 0 | J19: 0 | K19: 0
A20: Reversal of indemnifcation asset on expiry of underlying income tax provision | B20: - | C20: - | D20: - | E20: - | F20: - | G20: 34 | H20: 0 | I20: 0 | J20: 0 | K20: 0
A21: Inventory written off (net) | B21: 195 | C21: 145 | D21: 176 | E21: 155 | F21: 189 | G21: 225 | H21: 0 | I21: 0 | J21: 0 | K21: 0
A22: Bad debt / asset written off net of provision | B22: 74 | C22: -17 | D22: -34 | E22: -9 | F22: 18 | G22: 16 | H22: 0 | I22: 0 | J22: 0 | K22: 0
A23: Transaction cost on acquisition | B23: - | D23: 2 | E23: - | F23: - | G23: - | H23: 0 | I23: 0 | J23: 0 | K23: 0
A24: Profit on sale of brand rights | B24: - | C24: -29 | D24: -60 | E24: - | F24: - | G24: - | H24: 0 | I24: 0 | J24: 0 | K24: 0
A25: Equity sattleld share based payment expense | B25: -2 | C25: -1 | D25: - | E25: - | F25: 11 | G25: 16 | H25: 0 | I25: 0 | J25: 0 | K25: 0
A26: Gain on demerger of ice cream business | B26: - | C26: - | D26: - | E26: - | F26: - | G26: -4611 | H26: 0 | I26: 0 | J26: 0 | K26: 0
A27: Mark to market (gain) / loss on derivatives financial instrument | B27: 25 | C27: -1 | D27: -8 | E27: -8 | F27: 4 | G27: -109 | H27: 0 | I27: 0 | J27: 0 | K27: 0
A28: Cash generated from operations before working capital changes | B28: =SUM(B5:B27) -> 11380 | C28: =SUM(C5:C27) -> 12473 | D28: =SUM(D5:D27) -> 13557 | E28: =SUM(E5:E27) -> 14043 | F28: =SUM(F5:F27) -> 14343 | G28: =SUM(G5:G27) -> 14538 | H28: =SUM(H5:H27) -> 16143.965 | I28: =SUM(I5:I27) -> 17125.956 | ... K28: =SUM(K5:K27) -> 19280.312
A29: Adjustement for:
A30: (Increase)/decrease in Non current assets | B30: 1 | C30: 2 | D30: -13 | E30: -28 | F30: -117 | G30: 17
A31: (Increase)/decrease in current asset | B31: -395 | C31: -257 | D31: -1099 | E31: 170 | F31: -1057 | G31: -1 | H31: =-('Balance Sheet'!H24-'Balance Sheet'!G24) -> -63.726029 | I31: =-('Balance Sheet'!I24-'Balance Sheet'!H24) -> -196.03769 | J31: =-('Balance Sheet'!J24-'Balance Sheet'!I24) -> -208.43181 | K31: =-('Balance Sheet'!K24-'Balance Sheet'!J24) -> -221.60952
A32: (Increase)/decrease in inventory | B32: -472 | C32: -737 | D32: -332 | E32: 77 | F32: -540 | G32: -630 | H32: =-('Balance Sheet'!H21-'Balance Sheet'!G21) -> -266.43033 | I32: =-('Balance Sheet'!I21-'Balance Sheet'!H21) -> -293.95166 | J32: =-('Balance Sheet'!J21-'Balance Sheet'!I21) -> -312.53621 | K32: =-('Balance Sheet'!K21-'Balance Sheet'!J21) -> -332.29574
A33: (Increase)/decrease in non current liab | B33: 30 | C33: 92 | D33: -115 | E33: 144 | F33: 22 | G33: -169 | H33: 0 | I33: 0 | J33: 0 | K33: 0
A34: (Increase)/decrease in current liab | B34: 780 | C34: 111 | D34: 696 | E34: 773 | F34: 1138 | G34: 1467 | H34: ='Balance Sheet'!H58-'Balance Sheet'!G58 -> 820.70155 | I34: ='Balance Sheet'!I58-'Balance Sheet'!H58 -> 1561.3997 | J34: ='Balance Sheet'!J58-'Balance Sheet'!I58 -> 1703.937 | K34: ='Balance Sheet'!K58-'Balance Sheet'!J58 -> 1858.2565
A35: Cash flow generated from operations before tax | B35: =SUM(B28:B34) -> 11324 | C35: =SUM(C28:C34) -> 11684 | D35: =SUM(D28:D34) -> 12694 | E35: =SUM(E28:E34) -> 15179 | F35: =SUM(F28:F34) -> 13789 | G35: =SUM(G28:G34) -> 15222 | H35: =SUM(H28:H34) -> 16634.51 | I35: =SUM(I28:I34) -> 18197.367 | ... K35: =SUM(K28:K34) -> 20584.663
A36: Tax paid, net of refunds | B36: -2367 | C36: -2720 | D36: -3068 | E36: -295 | F36: -2183 | G36: -4726 | H36: =-('FY 26-27E Projected'!I23) -> -3622.062 | I36: =-('FY 26-27E Projected'!J23) -> -3831.6553 | J36: =-('FY 26-27E Projected'!K23) -> -4053.8854 | K36: =-('FY 26-27E Projected'!L23) -> -4289.5112
A37: Net cash flow generated from operation activities - (A) | B37: =B35+B36 -> 8957 | C37: =C35+C36 -> 8964 | D37: =D35+D36 -> 9626 | E37: =E35+E36 -> 14884 | F37: =F35+F36 -> 11606 | G37: =G35+G36 -> 10496 | H37: =H35+H36 -> 13012.448 | I37: =I35+I36 -> 14365.711 | ... K37: =K35+K36 -> 16295.152
A38: B CASH FLOWS FROM INVESTING ACTIVITIES:
A39: Purchase of property, plant, equipment | B39: -629 | C39: -916 | D39: -1023 | E39: -1309 | F39: -1128 | G39: -1171 | H39: =-(Assumption!G19*'FY 26-27E Projected'!I6) -> -1247.1495 | I39: =-(Assumption!H19*'FY 26-27E Projected'!J6) -> -1325.9983 | J39: =-(Assumption!I19*'FY 26-27E Projected'!K6) -> -1409.8321 | K39: =-(Assumption!J19*'FY 26-27E Projected'!L6) -> -1498.9661
A40: Sale proceed for property, plant and equipment | B40: 97 | C40: 146 | D40: 120 | E40: 20 | F40: 13 | G40: 29 | H40: 0 | I40: 0 | J40: 0 | K40: 0
A41: Purchase of intengible asset | B41: -3422 | C41: -3 | D41: -18 | E41: -9 | F41: -21 | G41: -103 | H41: 0 | I41: 0 | J41: 0 | K41: 0
A42: Sale proceeds of intangibles (brand rights) | B42: - | C42: 29 | D42: 60 | E42: - | F42: - | G42: - | H42: - | I42: 0 | J42: 0 | K42: 0
A43: Sale proceed for water purification business | B43: - | C43: - | D43: - | E43: - | F43: 595 | G43: - | H43: 0 | I43: 0 | J43: 0 | K43: 0
A44: Transaction cost on acquisition | B44: - | C44: - | D44: -2 | E44: - | F44: - | G44: - | H44: - | I44: 0 | J44: 0 | K44: 0
A45: Investment in Joint Venture | B45: - | C45: - | D45: -70 | E45: - | F45: - | G45: - | H45: - | I45: 0 | J45: 0 | K45: 0
A46: Investment in subsidiaries | B46: -60 | C46: -300 | D46: -264 | E46: - | F46: -5 | G46: -3530 | H46: 0 | I46: 0 | J46: 0 | K46: 0
A47: Consideration recevied in disposal of joint venture( net of transaction costs) | B47: -33 | C47: -41 | D47: -40 | E47: -4 | F47: - | G47: 298 | H47: 0 | I47: 0 | J47: 0 | K47: 0
A48: Purchase of non current asset | B48: - | C48: - | D48: - | E48: - | F48: - | G48: -111 | H48: 0 | I48: 0 | J48: 0 | K48: 0
A49: sale proceeds of non current investment | B49: - | C49: - | D49: - | E49: - | F49: - | G49: 1 | H49: 0 | I49: 0 | J49: 0 | K49: 0
A50: Purchase of current investments | B50: -38450 | C50: -47928 | D50: -22561 | E50: -21198 | F50: -20943 | G50: -22947 | H50: 0 | I50: 0 | J50: 0 | K50: 0
A51: Stamp duty on issue of equity shares | B51: -44 | C51: - | D51: - | E51: - | F51: - | G51: - | H51: - | I51: 0 | J51: 0 | K51: 0
A52: Sale proceeds of current investments | B52: 37076 | C52: 47173 | D52: 23363 | E52: 19752 | F52: 21984 | G52: 22608 | H52: 0 | I52: 0 | J52: 0 | K52: 0
A53: Loans given to subsidiaries | B53: -180 | C53: -436 | D53: -493 | E53: -431 | F53: -362 | G53: -171 | H53: 0 | I53: 0 | J53: 0 | K53: 0
A54: Loans repaid by subsidiaries | B54: 126 | C54: 284 | D54: 678 | E54: 381 | F54: 408 | G54: 158 | H54: 0 | I54: 0 | J54: 0 | K54: 0
A55: Loans given to others | B55: - | C55: -4 | D55: -1 | E55: 1 | F55: -11 | G55: -55 | H55: 0 | I55: 0 | J55: 0 | K55: 0
A56: Loans repaid by others | B56: - | C56: - | E56: - | F56: 11 | G56: 56 | H56: 0 | I56: 0 | J56: 0 | K56: 0
A57: Investment in term deposits (having original maturity of more than 3 months) | B57: -2375 | C57: -3619 | D57: -3627 | E57: -9080 | F57: -2486 | G57: -1912 | H57: 0 | I57: 0 | J57: 0 | K57: 0
A58: Redemption / maturity of term deposits ( having original maturity of more than 3 months) | B58: 6139 | C58: 3582 | D58: 2425 | E58: 6313 | F58: 7771 | G58: 2715 | H58: 0 | I58: 0 | J58: 0 | K58: 0
A59: Investment in non-current deposits | B59: - | C59: -1 | D59: - | E59: - | F59: - | G59: - | H59: - | I59: 0 | J59: 0 | K59: -
A60: Redemption / maturity of term deposits (with remaining maturity of more than 12 months) | B60: 1 | C60: - | D60: - | E60: - | F60: - | G60: 1 | H60: 0 | I60: 0 | J60: 0 | K60: 0
A61: Interest received | B61: 285 | C61: 171 | D61: 273 | E61: 417 | F61: 768 | G61: 431 | H61: 0 | I61: 0 | J61: 0 | K61: 0
A62: Dividend received from subsidiaries | B62: 101 | C62: 130 | D62: 116 | E62: 173 | F62: 169 | G62: 225 | H62: 0 | I62: 0 | J62: 0 | K62: 0
A63: Dividend received from others | B63: 1 | C63: 1 | D63: 2 | E63: 3 | F63: - | G63: 5 | H63: 0 | I63: 0 | J63: 0 | K63: 0
A64: Net cash flow ( used in )/ generated from investing activities - [B] | B64: =SUM(B39:B63) -> -1367 | C64: =SUM(C39:C63) -> -1732 | D64: =SUM(D39:D63) -> -1062 | E64: =SUM(E39:E63) -> -4971 | F64: =SUM(F39:F63) -> 6763 | G64: =SUM(G39:G63) -> -3473 | H64: =SUM(H39:H63) -> -1247.1495 | I64: =SUM(I39:I63) -> -1325.9983 | ... K64: =SUM(K39:K63) -> -1498.9661
A65: C CASH FLOWS FROM FINANCING ACTIVITIES:
A66: Dividend paids | B66: -8811 | C66: -7519 | D66: -8459 | E66: -9398 | F66: -12453 | G66: -10103 | H66: =-(Assumption!G20*'FY 26-27E Projected'!I24) -> -9947.3849 | I66: =-(Assumption!H20*'FY 26-27E Projected'!J24) -> -10522.998 | J66: =-(Assumption!I20*'FY 26-27E Projected'!K24) -> -11133.315 | K66: =-(Assumption!J20*'FY 26-27E Projected'!L24) -> -11780.422
A67: Principal payment of lease liabilities | B67: -383 | C67: -388 | D67: -431 | E67: -394 | F67: -460 | G67: -464 | H67: 0 | I67: 0 | J67: 0 | K67: 0
A68: Interest paid of lease liabilities | B68: -81 | C68: -75 | D68: -76 | E68: -98 | F68: -118 | G68: -117 | H68: 0 | I68: 0 | J68: 0 | K68: 0
A69: Interest paid other than on lease liabilities | B69: -5 | C69: -2 | D69: - | E69: - | F69: - | G69: - | H69: - | I69: 0 | J69: 0 | K69: 0
A70: Proceeds from share allotment under employee stock options/ performance share | B70: 0 | C70: 0 | D70: - | E70: - | F70: - | G70: - | H70: - | I70: 0 | J70: 0 | K70: 0
A71: Net cash flows used in financing activities - (C) | B71: =SUM(B66:B70) -> -9280 | C71: =SUM(C66:C70) -> -7984 | D71: =SUM(D66:D70) -> -8966 | E71: =SUM(E66:E70) -> -9890 | F71: =SUM(F66:F70) -> -13031 | G71: =SUM(G66:G70) -> -10684 | H71: =SUM(H66:H70) -> -9947.3849 | I71: =SUM(I66:I70) -> -10522.998 | ... K71: =SUM(K66:K70) -> -11780.422
A72: Net (decrese) / increase in cash and cash equvialnets [A]+[B]+[C] | B72: =B37+B64+B71 -> -1690 | C72: =C37+C64+C71 -> -752 | D72: =D37+D64+D71 -> -402 | E72: =E37+E64+E71 -> 23 | F72: =F37+F64+F71 -> 5338 | G72: =G37+G64+G71 -> -3661 | H72: =H37+H64+H71 -> 1817.9135 | I72: =I37+I64+I71 -> 2516.7153 | ... K72: =K37+K64+K71 -> 3015.7635
A73: Add: cash and cash equivalents at the begning of the year | B73: 3130 | C73: 1740 | D73: 988 | E73: 586 | F73: 609 | G73: 5947 | H73: ='Balance Sheet'!G25 -> 2286 | I73: ='Balance Sheet'!H25 -> 4103.9135 | J73: ='Balance Sheet'!I25 -> 6620.6288 | K73: ='Balance Sheet'!J25 -> 9376.6607
A74: Add: Cash acquired under Business Combination | B74: 300 | C74: - | D74: - | E74: - | F74: - | G74: - | H74: - | I74: - | J74: - | K74: -
A75: cash and cash equivalents at the end of the year | B75: =SUM(B73:B74)+B72 -> 1740 | C75: =SUM(C73:C74)+C72 -> 988 | D75: =SUM(D73:D74)+D72 -> 586 | E75: =SUM(E73:E74)+E72 -> 609 | F75: =SUM(F73:F74)+F72 -> 5947 | G75: =SUM(G73:G74)+G72 -> 2286 | H75: =SUM(H73:H74)+H72 -> 4103.9135 | I75: =SUM(I73:I74)+I72 -> 6620.6288 | ... K75: =SUM(K73:K74)+K72 -> 12392.424

Sheet Assumption
A1: HUL Standalone — Model Assumptions
A2: Base year: FY 2025-26 (actual) | Forecast year: FY 2026-27E
A4: Particulars | B4: As at 31st March 2022 | C4: As at 31st March 2023 | D4: As at 31st March 2024 | E4: As at 31st March 2025 | F4: As at 31st March 2026 | G4: As at 31 March 2027 E | H4: As at 31 March 2028 E | I4: As at 31 March 2029 E | J4: As at 31 March 2030 E
A5: Growth & margins
A6: Revenue growth % | B6: ='Income Statement'!D6/'Income Statement'!C6-1 -> 0.11298809 | C6: ='Income Statement'!E6/'Income Statement'!D6-1 -> 0.1553142 | D6: ='Income Statement'!F6/'Income Statement'!E6-1 -> 0.022402949 | E6: ='Income Statement'!G6/'Income Statement'!F6-1 -> -0.013114158 | F6: ='Income Statement'!H6/'Income Statement'!G6-1 -> 0.0385247 | G6: =AVERAGE($B$6:$F$6) -> 0.063223156 | H6: =AVERAGE($B$6:$F$6) -> 0.063223156 | I6: =AVERAGE($B$6:$F$6) -> 0.063223156 | J6: =AVERAGE($B$6:$F$6) -> 0.063223156 | K6: 5 year avg
A7: COGS % of revenue | B7: =('Income Statement'!D10+'Income Statement'!D11+'Income Statement'!D12)/'Income Statement'!D6 -> 0.49077022 | C7: =('Income Statement'!E10+'Income Statement'!E11+'Income Statement'!E12)/'Income Statement'!E6 -> 0.5265792 | D7: =('Income Statement'!F10+'Income Statement'!F11+'Income Statement'!F12)/'Income Statement'!F6 -> 0.48499231 | E7: =('Income Statement'!G10+'Income Statement'!G11+'Income Statement'!G12)/'Income Statement'!G6 -> 0.49212414 | F7: =('Income Statement'!H10+'Income Statement'!H11+'Income Statement'!H12)/'Income Statement'!H6 -> 0.50155708 | G7: =AVERAGE($B$7:$F$7) -> 0.49920459 | H7: =AVERAGE($B$7:$F$7) -> 0.49920459 | I7: =AVERAGE($B$7:$F$7) -> 0.49920459 | J7: =AVERAGE($B$7:$F$7) -> 0.49920459 | K7: 5 year avg
A8: Employee cost % of revenue | B8: ='Income Statement'!D13/'Income Statement'!D6 -> 0.046861876 | C8: ='Income Statement'!E13/'Income Statement'!E6 -> 0.045059516 | D8: ='Income Statement'!F13/'Income Statement'!F6 -> 0.046007045 | E8: ='Income Statement'!G13/'Income Statement'!G6 -> 0.045495677 | F8: ='Income Statement'!H13/'Income Statement'!H6 -> 0.045873336 | G8: =AVERAGE($B$8:$F$8) -> 0.04585949 | H8: =AVERAGE($B$8:$F$8) -> 0.04585949 | I8: =AVERAGE($B$8:$F$8) -> 0.04585949 | J8: =AVERAGE($B$8:$F$8) -> 0.04585949 | K8: 5 year avg
A9: Other expenses % of revenue | B9: ='Income Statement'!D16/'Income Statement'!D6 -> 0.21813529 | C9: ='Income Statement'!E16/'Income Statement'!E6 -> 0.19787299 | D9: ='Income Statement'!F16/'Income Statement'!F6 -> 0.23433495 | E9: ='Income Statement'!G16/'Income Statement'!G6 -> 0.22536698 | F9: ='Income Statement'!H16/'Income Statement'!H6 -> 0.21918516 | G9: =AVERAGE($B$9:$F$9) -> 0.21897907 | H9: =AVERAGE($B$9:$F$9) -> 0.21897907 | I9: =AVERAGE($B$9:$F$9) -> 0.21897907 | J9: =AVERAGE($B$9:$F$9) -> 0.21897907 | K9: 5 year avg
A10: Depreciation % of revenue | B10: ='Income Statement'!D15/'Income Statement'!D6 -> 0.020022269 | C10: ='Income Statement'!E15/'Income Statement'!E6 -> 0.017415122 | D10: ='Income Statement'!F15/'Income Statement'!F6 -> 0.018141527 | E10: ='Income Statement'!G15/'Income Statement'!G6 -> 0.018801528 | F10: ='Income Statement'!H15/'Income Statement'!H6 -> 0.019136749 | G10: =_xlfn.FORECAST.LINEAR(6, $C$10:$F$10, {2,3,4,5}) -> 0.019829952 | H10: =_xlfn.FORECAST.LINEAR(7, $C$10:$F$10, {2,3,4,5}) -> 0.02041244 | I10: =_xlfn.FORECAST.LINEAR(8, $C$10:$F$10, {2,3,4,5}) -> 0.020994928 | J10: =_xlfn.FORECAST.LINEAR(9, $C$10:$F$10, {2,3,4,5}) -> 0.021577416
A11: Effective tax rate | B11: =-('Income Statement'!D22+'Income Statement'!D23)/'Income Statement'!D20 -> 0.24882869 | C11: =-('Income Statement'!E22+'Income Statement'!E23)/'Income Statement'!E20 -> 0.23832097 | D11: =-('Income Statement'!F22+'Income Statement'!F23)/'Income Statement'!F20 -> 0.26040219 | E11: =-('Income Statement'!G22+'Income Statement'!G23)/'Income Statement'!G20 -> 0.25571159 | F11: =-('Income Statement'!H22+'Income Statement'!H23)/'Income Statement'!H20 -> 0.21732955 | G11: =AVERAGE($B$11:$F$11) -> 0.2441186 | H11: =AVERAGE($B$11:$F$11) -> 0.2441186 | I11: =AVERAGE($B$11:$F$11) -> 0.2441186 | J11: =AVERAGE($B$11:$F$11) -> 0.2441186 | K11: 5 year avg
A13: Working capital (days)
A14: Trade receivable days | B14: ='Balance Sheet'!C24/'Income Statement'!D6*365 -> 13.77493 | C14: ='Balance Sheet'!D24/'Income Statement'!E6*365 -> 16.87872 | D14: ='Balance Sheet'!E24/'Income Statement'!F6*365 -> 16.237246 | E14: ='Balance Sheet'!F24/'Income Statement'!G6*365 -> 21.101448 | F14: ='Balance Sheet'!G24/'Income Statement'!H6*365 -> 17.886325 | G14: =AVERAGE($B$14:$F$14) -> 17.175734 | H14: =AVERAGE($B$14:$F$14) -> 17.175734 | I14: =AVERAGE($B$14:$F$14) -> 17.175734 | J14: =AVERAGE($B$14:$F$14) -> 17.175734 | K14: 5 year avg
A15: Inventory days | B15: ='Balance Sheet'!C21/(('Income Statement'!D10+'Income Statement'!D11+'Income Statement'!D12))*365 -> 56.513692 | C15: ='Balance Sheet'!D21/(('Income Statement'!E10+'Income Statement'!E11+'Income Statement'!E12))*365 -> 47.242326 | D15: ='Balance Sheet'!E21/(('Income Statement'!F10+'Income Statement'!F11+'Income Statement'!F12))*365 -> 47.443653 | E15: ='Balance Sheet'!F21/(('Income Statement'!G10+'Income Statement'!G11+'Income Statement'!G12))*365 -> 51.714962 | F15: ='Balance Sheet'!G21/(('Income Statement'!H10+'Income Statement'!H11+'Income Statement'!H12))*365 -> 51.466832 | G15: =AVERAGE($E$15:$F$15) -> 51.590897 | H15: =AVERAGE($E$15:$F$15) -> 51.590897 | I15: =AVERAGE($E$15:$F$15) -> 51.590897 | J15: =AVERAGE($E$15:$F$15) -> 51.590897 | K15: 2 days avg
A16: Payable days | B16: =('Balance Sheet'!C52+'Balance Sheet'!C53)/('Income Statement'!D10+'Income Statement'!D11+'Income Statement'!D12)*365 -> 128.77567 | C16: =('Balance Sheet'!D52+'Balance Sheet'!D53)/(('Income Statement'!E10+'Income Statement'!E11+'Income Statement'!E12))*365 -> 110.0602 | D16: =('Balance Sheet'!E52+'Balance Sheet'!E53)/(('Income Statement'!F10+'Income Statement'!F11+'Income Statement'!F12))*365 -> 126.30068 | E16: =('Balance Sheet'!F52+'Balance Sheet'!F53)/(('Income Statement'!G10+'Income Statement'!G11+'Income Statement'!G12))*365 -> 136.68857 | F16: =('Balance Sheet'!G52+'Balance Sheet'!G53)/(('Income Statement'!H10+'Income Statement'!H11+'Income Statement'!H12))*365 -> 151.62929 | G16: =_xlfn.FORECAST.LINEAR(6, $B$16:$F$16, {1,2,3,4,5}) -> 152.39157 | H16: =_xlfn.FORECAST.LINEAR(7, $B$16:$F$16, {1,2,3,4,5}) -> 159.62513 | I16: =_xlfn.FORECAST.LINEAR(8, $B$16:$F$16, {1,2,3,4,5}) -> 166.85869 | J16: =_xlfn.FORECAST.LINEAR(9, $B$16:$F$16, {1,2,3,4,5}) -> 174.09225 | K16: FORECAST.LINEAR
A18: Capex & financing
A19: Capex % of revenue | B19: =-'Cash Flow Statement'!C39/'Income Statement'!D6 -> 0.017893071 | C19: =-'Cash Flow Statement'!D39/'Income Statement'!E6 -> 0.017296767 | D19: =-'Cash Flow Statement'!E39/'Income Statement'!F6 -> 0.021647456 | E19: =-'Cash Flow Statement'!F39/'Income Statement'!G6 -> 0.018902071 | F19: =-'Cash Flow Statement'!G39/'Income Statement'!H6 -> 0.018894716 | G19: =AVERAGE($B$19:$F$19) -> 0.018926816 | H19: =AVERAGE($B$19:$F$19) -> 0.018926816 | I19: =AVERAGE($B$19:$F$19) -> 0.018926816 | J19: =AVERAGE($B$19:$F$19) -> 0.018926816 | K19: 5 year avg
A20: Dividend payout ratio | B20: =-'Cash Flow Statement'!C66/'Income Statement'!D24 -> 0.85268768 | C20: =-'Cash Flow Statement'!D66/'Income Statement'!E24 -> 0.84912668 | D20: =-'Cash Flow Statement'!E66/'Income Statement'!F24 -> 0.92920704 | E20: =-'Cash Flow Statement'!F66/'Income Statement'!G24 -> 1.1689665 | F20: =-'Cash Flow Statement'!G66/'Income Statement'!H24 -> 0.91678766 | G20: =AVERAGE($B$20:$D$20,$F$20) -> 0.88695227 | H20: =AVERAGE($B$20:$D$20,$F$20) -> 0.88695227 | I20: =AVERAGE($B$20:$D$20,$F$20) -> 0.88695227 | J20: =AVERAGE($B$20:$D$20,$F$20) -> 0.88695227 | K20: 4 Year avg
C24: SENSITIVITY TESTS
D25: Growth% | E25: FY 30 Profit | G25: Payble days | H25: FY 30 closing cash | J25: COGS % | K25: FY 30 Profit
D26: =Assumption!G6 -> 0.063223156 | E26: ='FY 26-27E Projected'!L24 -> 13281.912 | G26: =J16 -> 174.09225 | H26: ='Cash Flow Statement'!K75 -> 12392.424 | J26: =G7 -> 0.49920459 | K26: ='FY 26-27E Projected'!L24 -> 13281.912
D27: 0.01 | E27: 12639.48 | G27: 100 | H27: 4366.9123 | J27: 0.48 | K27: 14431.581
D28: 0.02 | E28: 12760.185 | G28: 120 | H28: 6533.2688 | J28: 0.49 | K28: 13832.938
D29: 0.03 | E29: 12880.891 | G29: 140 | H29: 8699.6254 | J29: 0.5 | K29: 13234.295
D30: 0.0385 | E30: 12983.49 | G30: 151.6 | H30: 9956.1122 | J30: 0.5016 | K30: 13138.513
D31: 0.05 | E31: 13122.302 | G31: 160 | H31: 10865.982 | J31: 0.51 | K31: 12635.652
D32: 0.06 | E32: 13243.007 | G32: 180 | H32: 13032.339 | J32: 0.52 | K32: 12037.009
D33: 0.07 | E33: 13363.712 | G33: 200 | H33: 15198.695

Sheet FY 26-27E Projected
B1: HUL Standalone — Projected Financial Statement
B2: ₹ crore
B3: Particulars | C3: As at 31st March 2021 | D3: As at 31st March 2022 | E3: As at 31st March 2023 | F3: As at 31st March 2024 | G3: As at 31st March 2025 | H3: As at 31st March 2026 | I3: As at 31 March 2027 E | J3: As at 31 March 2028 E | K3: As at 31 March 2029 E | L3: As at 31 March 2030 E
B5: INCOME
B6: Revenue from operations | C6: =Table4[[#This Row],[As at 31st March 2021]] -> 45996 | D6: 51193 | E6: 59144 | F6: 60469 | G6: =Table4[[#This Row],[As at 31st March 2025]] -> 59676 | H6: =Table4[[#This Row],[As at 31st March 2026]] -> 61975 | I6: =H6*(1+Assumption!G6) -> 65893.255 | J6: =I6*(1+Assumption!H6) -> 70059.235 | K6: =J6*(1+Assumption!I6) -> 74488.601 | L6: =K6*(1+Assumption!J6) -> 79198.005
B7: Other income | C7: =Table4[[#This Row],[As at 31st March 2021]] -> 513 | D7: 393 | E7: 640 | F7: 973 | G7: =Table4[[#This Row],[As at 31st March 2025]] -> 1177 | H7: =Table4[[#This Row],[As at 31st March 2026]] -> 959 | I7: 959 | J7: 959 | K7: 959 | L7: 959
B8: TOTAL INCOME | C8: =SUM(C6:C7) -> 46509 | D8: =SUM(D6:D7) -> 51586 | E8: =SUM(E6:E7) -> 59784 | F8: =SUM(F6:F7) -> 61442 | G8: =SUM(G6:G7) -> 60853 | H8: =SUM(H6:H7) -> 62934 | I8: =SUM(I6:I7) -> 66852.255 | J8: =SUM(J6:J7) -> 71018.235 | ... L8: =SUM(L6:L7) -> 80157.005
B10: EXPENSES
B11: Cost of goods sold | C11: ='Income Statement'!C10 -> 14951 | D11: 15869 | E11: 19229 | F11: 17791 | G11: ='Income Statement'!G10 -> 17274 | H11: ='Income Statement'!H10 -> 18726 | I11: =I6*Assumption!G7 -> 32894.215 | J11: =J6*Assumption!H7 -> 34973.891 | K11: =K6*Assumption!I7 -> 37185.051 | L11: =L6*Assumption!J7 -> 39536.008
B12: Purchases of stock-in-trade | C12: ='Income Statement'!C11 -> 7117 | D12: 9274 | E12: 11968 | F12: 11544 | G12: ='Income Statement'!G11 -> 12172 | H12: ='Income Statement'!H11 -> 12753 | I12: 0 | J12: 0 | K12: 0 | L12: 0
B13: Changes in inventories of finished goods work-in-progress and stock-in-trade | C13: ='Income Statement'!C12 -> -391 | D13: -19 | E13: -53 | F13: -8 | G13: ='Income Statement'!G12 -> -78 | H13: ='Income Statement'!H12 -> -395 | I13: 0 | J13: 0 | K13: 0 | L13: 0
B14: Employee benefits expense | C14: ='Income Statement'!C13 -> 2229 | D14: 2399 | E14: 2665 | F14: 2782 | G14: ='Income Statement'!G13 -> 2715 | H14: ='Income Statement'!H13 -> 2843 | I14: =I6*Assumption!G8 -> 3021.8311 | J14: =J6*Assumption!H8 -> 3212.8808 | K14: =K6*Assumption!I8 -> 3416.0092 | L14: =L6*Assumption!J8 -> 3631.9801
B15: Finance costs | C15: ='Income Statement'!C14 -> 108 | D15: 98 | E15: 101 | F15: 302 | G15: ='Income Statement'!G14 -> 350 | H15: ='Income Statement'!H14 -> 363 | I15: 363 | J15: 364 | K15: 365 | L15: 366
B16: Depreciation and amortisation expense | C16: ='Income Statement'!C15 -> 1012 | D16: 1025 | E16: 1030 | F16: 1097 | G16: ='Income Statement'!G15 -> 1122 | H16: ='Income Statement'!H15 -> 1186 | I16: =I6*Assumption!G10 -> 1306.6601 | J16: =J6*Assumption!H10 -> 1430.0799 | K16: =K6*Assumption!I10 -> 1563.8828 | L16: =L6*Assumption!J10 -> 1708.8883
B17: Other expenses | C17: ='Income Statement'!C16 -> 10766 | D17: 11167 | E17: 11703 | F17: 14170 | G17: ='Income Statement'!G16 -> 13449 | H17: ='Income Statement'!H16 -> 13584 | I17: =I6*Assumption!G9 -> 14429.244 | J17: =J6*Assumption!H9 -> 15341.506 | K17: =K6*Assumption!I9 -> 16311.445 | L17: =L6*Assumption!J9 -> 17342.706
B18: TOTAL EXPENSES | C18: ='Income Statement'!C17 -> 35792 | D18: =SUM(D11:D17) -> 39813 | E18: =SUM(E11:E17) -> 46643 | F18: =SUM(F11:F17) -> 47678 | G18: =SUM(G11:G17) -> 47004 | H18: =SUM(H11:H17) -> 49060 | I18: =SUM(I11:I17) -> 52014.95 | J18: =SUM(J11:J17) -> 55322.358 | K18: =SUM(K11:K17) -> 58841.388 | L18: =SUM(L11:L17) -> 62585.582
B20: Profit before exceptional items and tax (EBIT) | C20: ='Income Statement'!C18 -> 10717 | D20: 11773 | E20: 13141 | F20: 13764 | G20: ='Income Statement'!G18 -> 13849 | H20: ='Income Statement'!H18 -> 13874 | I20: =I8-I18 -> 14837.305 | J20: =J8-J18 -> 15695.876 | K20: =K8-K18 -> 16606.213 | L20: =L8-L18 -> 17571.423
B21: Exceptional items | C21: ='Income Statement'!C19 -> -227 | D21: -34 | E21: -62 | F21: -89 | G21: ='Income Statement'!G19 -> 464 | H21: ='Income Statement'!H19 -> 206 | I21: 0 | J21: 0 | K21: 0 | L21: 0
B22: Profit before tax (PBT) | C22: =SUM(C20:C21) -> 10490 | D22: =SUM(D20:D21) -> 11739 | E22: =SUM(E20:E21) -> 13079 | F22: =SUM(F20:F21) -> 13675 | G22: =SUM(G20:G21) -> 14313 | H22: =SUM(H20:H21) -> 14080 | I22: =SUM(I20:I21) -> 14837.305 | J22: =SUM(J20:J21) -> 15695.876 | ... L22: =SUM(L20:L21) -> 17571.423
B23: Tax expense | C23: ='Income Statement'!C22+Table4[[#This Row],[As at 31st March 2021]] -> -2536 | D23: =-2778-143 -> -2921 | E23: =-2922-195 -> -3117 | F23: =-3446-115 -> -3561 | G23: =SUM('Income Statement'!G22:G23) -> -3660 | H23: =SUM('Income Statement'!H22:H23) -> -3060 | I23: =I22*Assumption!G11 -> 3622.062 | J23: =J22*Assumption!H11 -> 3831.6553 | K23: =K22*Assumption!I11 -> 4053.8854 | L23: =L22*Assumption!J11 -> 4289.5112
B24: PROFIT FOR THE YEAR | C24: =C22+C23 -> 7954 | D24: =D22+D23 -> 8818 | E24: =E22+E23 -> 9962 | F24: =F22+F23 -> 10114 | G24: =G22+G23 -> 10653 | H24: =H22+H23 -> 11020 | I24: =I22-I23 -> 11215.243 | J24: =J22-J23 -> 11864.221 | K24: =K22-K23 -> 12552.327 | L24: =L22-L23 -> 13281.912
B25: EBITDA | C25: =C20+C16 -> 11729 | D25: =D20+D16 -> 12798 | E25: =E20+E16 -> 14171 | F25: =F20+F16 -> 14861 | G25: =G20+G16 -> 14971 | H25: =H20+H16 -> 15060 | I25: =I20+I16 -> 16143.965 | J25: =J20+J16 -> 17125.956 | ... L25: =L20+L16 -> 19280.312
B26: Gross Profit | C26: =C6-C11-C12-C13 -> 24319 | D26: =D6-D11-D12-D13 -> 26069 | E26: =E6-E11-E12-E13 -> 28000 | F26: =F6-F11-F12-F13 -> 31142 | G26: =G6-G11-G12-G13 -> 30308 | H26: =H6-H11-H12-H13 -> 30891 | I26: =I6-I11-I12-I13 -> 32999.04 | J26: =J6-J11-J12-J13 -> 35085.343 | ... L26: =L6-L11-L12-L13 -> 39661.997

Sheet Ratios
A1: HUL Financial Ratios
A2: Historical and forecast ratio analysis
A3: Particulars | B3: As at 31st March 2021 | C3: As at 31st March 2022 | D3: As at 31st March 2023 | E3: As at 31st March 2024 | F3: As at 31st March 2025 | G3: As at 31st March 2026 | H3: As at 31 March 2027 E | I3: As at 31 March 2028 E | J3: As at 31 March 2029 E | K3: As at 31 March 2030 E
A5: Net Profit Margin % | B5: ='Income Statement'!C24/'Income Statement'!C6 -> 0.17292808 | C5: ='Income Statement'!D24/'Income Statement'!D6 -> 0.17225011 | D5: ='Income Statement'!E24/'Income Statement'!E6 -> 0.16843636 | E5: ='Income Statement'!F24/'Income Statement'!F6 -> 0.16725926 | F5: ='Income Statement'!G24/'Income Statement'!G6 -> 0.17851398 | G5: ='Income Statement'!H24/'Income Statement'!H6 -> 0.17781363 | H5: ='FY 26-27E Projected'!I24/'FY 26-27E Projected'!I6 -> 0.1702032 | I5: ='FY 26-27E Projected'!J24/'FY 26-27E Projected'!J6 -> 0.16934557 | J5: ='FY 26-27E Projected'!K24/'FY 26-27E Projected'!K6 -> 0.1685134 | K5: ='FY 26-27E Projected'!L24/'FY 26-27E Projected'!L6 -> 0.16770513
A6: Gross Margin % | B6: =(Table4[[#This Row],[As at 31st March 2021]]-('Income Statement'!C10+'Income Statement'!C11+'Income Statement'!C12))/Table4[[#This Row],[As at 31st March 2021]] -> 0.52871989 | C6: =(Table4[[#This Row],[As at 31st March 2022]]-('Income Statement'!D10+'Income Statement'!D11+'Income Statement'!D12))/Table4[[#This Row],[As at 31st March 2022]] -> 0.50922978 | D6: =(Table4[[#This Row],[As at 31st March 2023]]-('Income Statement'!E10+'Income Statement'!E11+'Income Statement'!E12))/Table4[[#This Row],[As at 31st March 2023]] -> 0.4734208 | E6: =(Table4[[#This Row],[As at 31st March 2024]]-('Income Statement'!F10+'Income Statement'!F11+'Income Statement'!F12))/Table4[[#This Row],[As at 31st March 2024]] -> 0.51500769 | F6: =(Table4[[#This Row],[As at 31st March 2025]]-('Income Statement'!G10+'Income Statement'!G11+'Income Statement'!G12))/Table4[[#This Row],[As at 31st March 2025]] -> 0.50787586 | G6: =(Table4[[#This Row],[As at 31st March 2026]]-('Income Statement'!H10+'Income Statement'!H11+'Income Statement'!H12))/Table4[[#This Row],[As at 31st March 2026]] -> 0.49844292 | H6: =1-Assumption!G7 -> 0.50079541 | I6: =1-Assumption!H7 -> 0.50079541 | J6: =1-Assumption!I7 -> 0.50079541 | K6: =1-Assumption!J7 -> 0.50079541
A7: Operating Margin % | B7: =('Income Statement'!C20+'Income Statement'!C14)/'Income Statement'!C6 -> 0.23041134 | C7: =('Income Statement'!D20+'Income Statement'!D14)/'Income Statement'!D6 -> 0.23122302 | D7: =('Income Statement'!E20+'Income Statement'!E14)/'Income Statement'!E6 -> 0.22284594 | E7: =('Income Statement'!F20+'Income Statement'!F14)/'Income Statement'!F6 -> 0.23114323 | F7: =('Income Statement'!G20+'Income Statement'!G14)/'Income Statement'!G6 -> 0.24571017 | G7: =('Income Statement'!H20+'Income Statement'!H14)/'Income Statement'!H6 -> 0.23304558 | H7: =('FY 26-27E Projected'!I22+'FY 26-27E Projected'!I15)/'FY 26-27E Projected'!I6 -> 0.23068074 | I7: =('FY 26-27E Projected'!J22+'FY 26-27E Projected'!J15)/'FY 26-27E Projected'!J6 -> 0.22923283 | J7: =('FY 26-27E Projected'!K22+'FY 26-27E Projected'!K15)/'FY 26-27E Projected'!K6 -> 0.22783637 | K7: =('FY 26-27E Projected'!L22+'FY 26-27E Projected'!L15)/'FY 26-27E Projected'!L6 -> 0.22648832
A8: ROE | B8: ='Income Statement'!C24/'Balance Sheet'!B38 -> 0.16768563 | C8: ='Income Statement'!D24/'Balance Sheet'!C38 -> 0.18084495 | D8: ='Income Statement'!E24/'Balance Sheet'!D38 -> 0.19836323 | E8: ='Income Statement'!F24/'Balance Sheet'!E38 -> 0.19841877 | F8: ='Income Statement'!G24/'Balance Sheet'!F38 -> 0.21673143 | G8: ='Income Statement'!H24/'Balance Sheet'!G38 -> 0.22387908 | H8: ='FY 26-27E Projected'!I24/'Balance Sheet'!H38 -> 0.22212423 | I8: ='FY 26-27E Projected'!J24/'Balance Sheet'!I38 -> 0.22889725 | J8: ='FY 26-27E Projected'!K24/'Balance Sheet'!J38 -> 0.23571962 | K8: ='FY 26-27E Projected'!L24/'Balance Sheet'!K38 -> 0.24258056
A9: Current Ratio | B9: ='Balance Sheet'!B32/'Balance Sheet'!B58 -> 1.2581865 | C9: ='Balance Sheet'!C32/'Balance Sheet'!C58 -> 1.3383589 | D9: ='Balance Sheet'!D32/'Balance Sheet'!D58 -> 1.3803217 | E9: ='Balance Sheet'!E32/'Balance Sheet'!E58 -> 1.6363783 | F9: ='Balance Sheet'!F32/'Balance Sheet'!F58 -> 1.3335248 | G9: ='Balance Sheet'!G32/'Balance Sheet'!G58 -> 1.1729882 | H9: ='Balance Sheet'!H32/'Balance Sheet'!H58 -> 1.2481574 | I9: ='Balance Sheet'!I32/'Balance Sheet'!I58 -> 1.309194 | ... K9: ='Balance Sheet'!K32/'Balance Sheet'!K58 -> 1.4136805
A10: Quick Ratio | B10: =('Balance Sheet'!B32-'Balance Sheet'!B21)/'Balance Sheet'!B58 -> 0.94613043 | C10: =('Balance Sheet'!C32-'Balance Sheet'!C21)/'Balance Sheet'!C58 -> 0.98291301 | D10: =('Balance Sheet'!D32-'Balance Sheet'!D21)/'Balance Sheet'!D58 -> 1.0336286 | E10: =('Balance Sheet'!E32-'Balance Sheet'!E21)/'Balance Sheet'!E58 -> 1.3290333 | F10: =('Balance Sheet'!F32-'Balance Sheet'!F21)/'Balance Sheet'!F58 -> 1.0680194 | G10: =('Balance Sheet'!G32-'Balance Sheet'!G21)/'Balance Sheet'!G58 -> 0.87979129 | H10: =('Balance Sheet'!H32-'Balance Sheet'!H21)/'Balance Sheet'!H58 -> 0.95332429 | I10: =('Balance Sheet'!I32-'Balance Sheet'!I21)/'Balance Sheet'!I58 -> 1.0239622 | ... K10: =('Balance Sheet'!K32-'Balance Sheet'!K21)/'Balance Sheet'!K58 -> 1.146216
A11: Cash Conversion Cycle (days) | C11: =Assumption!B14+Assumption!B15-Assumption!B16 -> -58.48705 | D11: =Assumption!C14+Assumption!C15-Assumption!C16 -> -45.939159 | E11: =Assumption!D14+Assumption!D15-Assumption!D16 -> -62.61978 | F11: =Assumption!E14+Assumption!E15-Assumption!E16 -> -63.872163 | G11: =Assumption!F14+Assumption!F15-Assumption!F16 -> -82.276138 | H11: =Assumption!G14+Assumption!G15-Assumption!G16 -> -83.624938 | I11: =Assumption!H14+Assumption!H15-Assumption!H16 -> -90.858499 | J11: =Assumption!I14+Assumption!I15-Assumption!I16 -> -98.09206 | K11: =Assumption!J14+Assumption!J15-Assumption!J16 -> -105.32562
A12: Debt to Equity | B12: =('Balance Sheet'!B58+'Balance Sheet'!B47)/'Balance Sheet'!B38 -> 0.43601636 | C12: =('Balance Sheet'!C58+'Balance Sheet'!C47)/'Balance Sheet'!C38 -> 0.43020919 | D12: =('Balance Sheet'!D58+'Balance Sheet'!D47)/'Balance Sheet'!D38 -> 0.43017861 | E12: =('Balance Sheet'!E58+'Balance Sheet'!E47)/'Balance Sheet'!E38 -> 0.51209464 | F12: =('Balance Sheet'!F58+'Balance Sheet'!F47)/'Balance Sheet'!F38 -> 0.59324965 | G12: =('Balance Sheet'!G58+'Balance Sheet'!G47)/'Balance Sheet'!G38 -> 0.58425939 | H12: =('Balance Sheet'!H58+'Balance Sheet'!H47)/'Balance Sheet'!H38 -> 0.58584272 | I12: =('Balance Sheet'!I58+'Balance Sheet'!I47)/'Balance Sheet'!I38 -> 0.60080747 | ... K12: =('Balance Sheet'!K58+'Balance Sheet'!K47)/'Balance Sheet'!K38 -> 0.63382023
A13: Interest Coverage | B13: ='FY 26-27E Projected'!C20/'FY 26-27E Projected'!C15 -> 99.231481 | C13: ='FY 26-27E Projected'!D20/'FY 26-27E Projected'!D15 -> 120.13265 | D13: ='FY 26-27E Projected'!E20/'FY 26-27E Projected'!E15 -> 130.10891 | E13: ='FY 26-27E Projected'!F20/'FY 26-27E Projected'!F15 -> 45.576159 | F13: ='FY 26-27E Projected'!G20/'FY 26-27E Projected'!G15 -> 39.568571 | G13: ='FY 26-27E Projected'!H20/'FY 26-27E Projected'!H15 -> 38.220386 | H13: =('FY 26-27E Projected'!I22+'FY 26-27E Projected'!I15)/'FY 26-27E Projected'!I15 -> 41.874118 | I13: =('FY 26-27E Projected'!J22+'FY 26-27E Projected'!J15)/'FY 26-27E Projected'!J15 -> 44.120539 | J13: =('FY 26-27E Projected'!K22+'FY 26-27E Projected'!K15)/'FY 26-27E Projected'!K15 -> 46.496473 | K13: =('FY 26-27E Projected'!L22+'FY 26-27E Projected'!L15)/'FY 26-27E Projected'!L15 -> 49.009353
A14: EBITDA Margin % | B14: ='FY 26-27E Projected'!C25/'FY 26-27E Projected'!C6 -> 0.25500043 | C14: ='FY 26-27E Projected'!D25/'FY 26-27E Projected'!D6 -> 0.24999512 | D14: ='FY 26-27E Projected'!E25/'FY 26-27E Projected'!E6 -> 0.23960165 | E14: ='FY 26-27E Projected'!F25/'FY 26-27E Projected'!F6 -> 0.24576229 | F14: ='FY 26-27E Projected'!G25/'FY 26-27E Projected'!G6 -> 0.25087137 | G14: ='FY 26-27E Projected'!H25/'FY 26-27E Projected'!H6 -> 0.24300121 | H14: ='FY 26-27E Projected'!I25/'FY 26-27E Projected'!I6 -> 0.24500178 | I14: ='FY 26-27E Projected'!J25/'FY 26-27E Projected'!J6 -> 0.24444966 | ... K14: ='FY 26-27E Projected'!L25/'FY 26-27E Projected'!L6 -> 0.24344441
A15: ROA | B15: ='FY 26-27E Projected'!C24/'Balance Sheet'!B33 -> 0.11677139 | C15: ='FY 26-27E Projected'!D24/'Balance Sheet'!C33 -> 0.12644651 | D15: ='FY 26-27E Projected'!E24/'Balance Sheet'!D33 -> 0.13869822 | E15: ='FY 26-27E Projected'!F24/'Balance Sheet'!E33 -> 0.13122113 | F15: ='FY 26-27E Projected'!G24/'Balance Sheet'!F33 -> 0.13603105 | G15: ='FY 26-27E Projected'!H24/'Balance Sheet'!G33 -> 0.14131466 | H15: ='FY 26-27E Projected'!I24/'Balance Sheet'!H33 -> 0.140067 | I15: ='FY 26-27E Projected'!J24/'Balance Sheet'!I33 -> 0.14298862 | ... K15: ='FY 26-27E Projected'!L24/'Balance Sheet'!K33 -> 0.14847445

Sheet DAS DATA
A1: Year | B1: Gross Margin % | C1: EBITDA Margin % | D1: Net Profit Margin % | G1: Year | H1: Operating CF | I1: Investing CF | J1: Financing CF | L1: Asset | M1: FY25-26
A2: FY20-21 | B2: =Ratios!B6 -> 0.52871989 | C2: =Ratios!B14 -> 0.25500043 | D2: =Ratios!B5 -> 0.17292808 | G2: FY21 | H2: ='Cash Flow Statement'!B37 -> 8957 | I2: ='Cash Flow Statement'!B64 -> -1367 | J2: ='Cash Flow Statement'!B71 -> -9280 | L2: Cash & Cash Equivalents | M2: ='Balance Sheet'!G25 -> 2286
A3: FY21-22 | B3: =Ratios!C6 -> 0.50922978 | C3: =Ratios!C14 -> 0.24999512 | D3: =Ratios!C5 -> 0.17225011 | G3: FY22 | H3: ='Cash Flow Statement'!C$37 -> 8964 | I3: ='Cash Flow Statement'!C64 -> -1732 | J3: ='Cash Flow Statement'!C71 -> -7984 | L3: Trade Receivables | M3: ='Balance Sheet'!G24 -> 3037
A4: FY22-23 | B4: =Ratios!D6 -> 0.4734208 | C4: =Ratios!D14 -> 0.23960165 | D4: =Ratios!D5 -> 0.16843636 | G4: FY23 | H4: ='Cash Flow Statement'!D37 -> 9626 | I4: ='Cash Flow Statement'!D64 -> -1062 | J4: ='Cash Flow Statement'!D71 -> -8966 | L4: Inventories | M4: ='Balance Sheet'!G21 -> 4383
A5: FY23-24 | B5: =Ratios!E6 -> 0.51500769 | C5: =Ratios!E14 -> 0.24576229 | D5: =Ratios!E5 -> 0.16725926 | G5: FY24 | H5: ='Cash Flow Statement'!E37 -> 14884 | I5: ='Cash Flow Statement'!E64 -> -4971 | J5: ='Cash Flow Statement'!E71 -> -9890 | L5: Other Current Assets | M5: ='Balance Sheet'!G30 -> 985
A6: FY24-25 | B6: =Ratios!F6 -> 0.50787586 | C6: =Ratios!F14 -> 0.25087137 | D6: =Ratios!F5 -> 0.17851398 | G6: FY25 | H6: ='Cash Flow Statement'!F37 -> 11606 | I6: ='Cash Flow Statement'!F64 -> 6763 | J6: ='Cash Flow Statement'!F71 -> -13031 | L6: Property, Plant & Equipment (PPE) | M6: ='Balance Sheet'!G8 -> 7191
A7: FY25-26A | B7: =Ratios!G6 -> 0.49844292 | C7: =Ratios!G14 -> 0.24300121 | D7: =Ratios!G5 -> 0.17781363 | G7: FY26 | H7: ='Cash Flow Statement'!G37 -> 10496 | I7: ='Cash Flow Statement'!G64 -> -3473 | J7: ='Cash Flow Statement'!G71 -> -10684 | L7: Other Non-Current Assets | M7: ='Balance Sheet'!G18 -> 340
A8: FY26-27E | B8: =Ratios!H6 -> 0.50079541 | C8: =Ratios!H14 -> 0.24500178 | D8: =Ratios!H5 -> 0.1702032 | G8: FY27E | H8: ='Cash Flow Statement'!H37 -> 13012.448 | I8: ='Cash Flow Statement'!H64 -> -1247.1495 | J8: ='Cash Flow Statement'!H71 -> -9947.3849
A9: FY27-28E | B9: =Ratios!I6 -> 0.50079541 | C9: =Ratios!I14 -> 0.24444966 | D9: =Ratios!I5 -> 0.16934557 | G9: FY28E | H9: ='Cash Flow Statement'!I37 -> 14365.711 | I9: ='Cash Flow Statement'!I64 -> -1325.9983 | J9: ='Cash Flow Statement'!I71 -> -10522.998
A10: FY28-29E | B10: =Ratios!J6 -> 0.50079541 | C10: =Ratios!J14 -> 0.24393122 | D10: =Ratios!J5 -> 0.1685134 | G10: FY29E | H10: ='Cash Flow Statement'!J37 -> 15299.179 | I10: ='Cash Flow Statement'!J64 -> -1409.8321 | J10: ='Cash Flow Statement'!J71 -> -11133.315
A11: FY29-30E | B11: =Ratios!K6 -> 0.50079541 | C11: =Ratios!K14 -> 0.24344441 | D11: =Ratios!K5 -> 0.16770513 | G11: FY30E | H11: ='Cash Flow Statement'!K37 -> 16295.152 | I11: ='Cash Flow Statement'!K64 -> -1498.9661 | J11: ='Cash Flow Statement'!K71 -> -11780.422
A14: Dashboard Ratio | B14: Source | D14: Year | E14: Historical | F14: Forecast | H14: Liability | I14: FY25-26A
A15: Current Ratio | B15: =Ratios!G9 -> 1.1729882 | D15: FY20-21 | E15: ='FY 26-27E Projected'!C6 -> 45996 | H15: Current Liabilities | I15: ='Balance Sheet'!G58 -> 14949
A16: Quick Ratio | B16: =Ratios!G10 -> 0.87979129 | D16: FY21-22 | E16: ='FY 26-27E Projected'!D6 -> 51193 | H16: Non-Current Liabilities | I16: ='Balance Sheet'!G47 -> 13810
A17: Debt to Equity | B17: =Ratios!G12 -> 0.58425939 | D17: FY22-23 | E17: ='FY 26-27E Projected'!E6 -> 59144 | H17: Share Capital | I17: ='Balance Sheet'!G36 -> 235
A18: ROE | B18: =Ratios!G8 -> 0.22387908 | D18: FY23-24 | E18: ='FY 26-27E Projected'!F6 -> 60469 | H18: Other Equity (Reserves) | I18: ='Balance Sheet'!G37 -> 48988
A19: ROA | B19: =Ratios!G15 -> 0.14131466 | D19: FY24-25 | E19: ='FY 26-27E Projected'!G6 -> 59676
A20: Gross Margin | B20: =Ratios!G6 -> 0.49844292 | D20: FY25-26A | E20: ='FY 26-27E Projected'!H6 -> 61975
A21: EBITDA Margin | B21: =C7 -> 0.24300121 | D21: FY26-27E | F21: ='FY 26-27E Projected'!I6 -> 65893.255
A22: Net Profit Margin | B22: =D7 -> 0.17781363 | D22: FY27-28E | F22: ='FY 26-27E Projected'!J6 -> 70059.235
D23: FY28-29E | F23: ='FY 26-27E Projected'!K6 -> 74488.601
D24: FY29-30E | F24: ='FY 26-27E Projected'!L6 -> 79198.005
